xfdfgen/__init__.py
xfdfgen/xfdfgen.py
xfdfgen-0.4.dist-info/LICENSE
xfdfgen-0.4.dist-info/METADATA
xfdfgen-0.4.dist-info/WHEEL
xfdfgen-0.4.dist-info/top_level.txt
xfdfgen-0.4.dist-info/RECORD
