Metadata-Version: 2.1
Name: xfdfgen
Version: 0.4
Summary: xfdfgen is a Python library for creating xfdf files that can be used to populate pdf form fields.
Home-page: https://github.com/Balonger/xfdfgen
Author: Nguyen Ba Long
Author-email: Nguyen.Ba.Long13@gmail.com
License: APACHE 2.0
Platform: UNKNOWN
Classifier: Development Status :: 3 - Alpha
Classifier: License :: OSI Approved :: Apache Software License
Classifier: Programming Language :: Python
Classifier: Programming Language :: Python :: 3.7
Classifier: Topic :: Software Development :: Libraries
Classifier: Topic :: Software Development :: Libraries :: Python Modules
Classifier: Intended Audience :: Developers
Requires-Python: >=3.7
